STCase/__init__.py
STCase/ccci.py
STCase/data_handler.py
STCase/model.py
STCase/pipeline.py
STCase/pl.py
STCase/tl.py
STCase/trainer.py
STCase/utils.py
stcase-1.0.0.dist-info/METADATA
stcase-1.0.0.dist-info/WHEEL
stcase-1.0.0.dist-info/RECORD
