Metadata-Version: 2.1
Name: STCase
Version: 1.0.0
Summary: Spatial Transcriptomics cell-cell Communication and subtype exploration
Author: Lzcstan
Author-email: lzcstan@outlook.com
Classifier: Programming Language :: Python :: 2
Classifier: Programming Language :: Python :: 2.7
Classifier: Programming Language :: Python :: 3
Classifier: Programming Language :: Python :: 3.4
Classifier: Programming Language :: Python :: 3.5
Classifier: Programming Language :: Python :: 3.6
Classifier: Programming Language :: Python :: 3.7
Classifier: Programming Language :: Python :: 3.8
Classifier: Programming Language :: Python :: 3.9
Classifier: Programming Language :: Python :: 3.10
Classifier: Programming Language :: Python :: 3.11
Requires-Dist: anndata
Requires-Dist: arboreto
Requires-Dist: ctxcore
Requires-Dist: ipykernel
Requires-Dist: kneed
Requires-Dist: leidenalg
Requires-Dist: louvain
Requires-Dist: matplotlib
Requires-Dist: netgraph
Requires-Dist: pandas
Requires-Dist: plotnine
Requires-Dist: pot
Requires-Dist: pycirclize
Requires-Dist: pyg_lib
Requires-Dist: pyscenic
Requires-Dist: rich
Requires-Dist: scanpy
Requires-Dist: scikit-learn
Requires-Dist: scikit-misc
Requires-Dist: scipy
Requires-Dist: torch
Requires-Dist: torch-cluster
Requires-Dist: torch-geometric
Requires-Dist: torch-scatter
Requires-Dist: torch-sparse
Requires-Dist: torch-spline-conv
Project-URL: documentation, https://stcase.readthedocs.io/en/latest/tutorial/index.html
Project-URL: homepage, https://stcase.readthedocs.io
Project-URL: repository, https://github.com/Lzcstan/STCase
